arangodantic/__init__.py
arangodantic/arangdb_error_codes.py
arangodantic/asynccontextmanager.py
arangodantic/configurations.py
arangodantic/cursor.py
arangodantic/directions.py
arangodantic/exceptions.py
arangodantic/graphs.py
arangodantic/models.py
arangodantic/tests/__init__.py
arangodantic/tests/conftest.py
arangodantic/tests/test_cursor.py
arangodantic/tests/test_graph.py
arangodantic/tests/test_model.py
arangodantic/utils.py
arangodantic-0.3.1.dist-info/LICENSE
arangodantic-0.3.1.dist-info/WHEEL
arangodantic-0.3.1.dist-info/METADATA
arangodantic-0.3.1.dist-info/RECORD
