Metadata-Version: 2.1
Name: arangodantic
Version: 0.3.1
Summary: Database models for ArangoDB using Pydantic base models.
Home-page: https://github.com/ioxiocom/arangodantic
License: BSD-3-Clause
Author: Digital Living International Ltd
Requires-Python: >=3.7,<4.0
Classifier: License :: OSI Approved :: BSD License
Classifier: Programming Language :: Python :: 3
Classifier: Programming Language :: Python :: 3.10
Classifier: Programming Language :: Python :: 3.7
Classifier: Programming Language :: Python :: 3.8
Classifier: Programming Language :: Python :: 3.9
Provides-Extra: shylock
Requires-Dist: aioarangodb (>=0.1.2,<0.2.0)
Requires-Dist: inflection (>=0.5.1,<0.6.0)
Requires-Dist: pydantic (>=1.9.1,<2.0.0)
Requires-Dist: shylock[aioarangodb] (>=1.1.1,<2.0.0); extra == "shylock"
Project-URL: Repository, https://github.com/ioxiocom/arangodantic
